{
  "LEMONSPIRE.stats.title": "统计",
  "LEMONSPIRE.stats.combat": "本局",
  "LEMONSPIRE.stats.total": "总计",
  "LEMONSPIRE.stats.combat.damage": "伤害",
  "LEMONSPIRE.stats.combat.extra_damage": "被增益伤害",
  "LEMONSPIRE.stats.combat.buffs_applied": "施加增益",
  "LEMONSPIRE.stats.combat.debuffs_applied": "施加减益",
  "LEMONSPIRE.stats.total.damage": "伤害",
  "LEMONSPIRE.stats.total.extra_damage": "被增益伤害",
  "LEMONSPIRE.stats.total.buffs_applied": "施加增益",
  "LEMONSPIRE.stats.total.debuffs_applied": "施加减益",
  "LEMONSPIRE.chat.placeholder": "输入消息...",
  "LEMONSPIRE.chat.welcome": "按 [Tab] 打开聊天",
  "LEMONSPIRE.chat.title": "柠檬聊天",
  "LEMONSPIRE.chat.handCardShare": "的手牌 ",
  "LEMONSPIRE.chat.cardRewardShare": "的卡牌奖励 ",
  "LEMONSPIRE.chat.potionShare": "的药水 ",
  "LEMONSPIRE.chat.shopShare": "的商店物品 ",
  "LEMONSPIRE.chat.powerOwnerPrefix": "{Owner}的 ",
  "LEMONSPIRE.panel.hand": "手牌",
  "LEMONSPIRE.panel.potions": "药水",
  "LEMONSPIRE.panel.shop": "商店",
  "LEMONSPIRE.panel.cardRewards": "卡牌奖励",
  "LEMONSPIRE.color_picker.title": "选择颜色",
  "LEMONSPIRE.color_picker.tooltip": "选择玩家颜色",
  "LEMONSPIRE.shop.empty": "暂无商品",
  "LEMONSPIRE.shop.gold": "金币",
  "LEMONSPIRE.cardRewards.empty": "暂无奖励",
  "LEMONSPIRE.cardRewards.normal": "奖励",
  "LEMONSPIRE.cardRewards.special": "特殊"
}
